verilog_parser/__init__.py
verilog_parser/parser.py
verilog_parser/test_data.py
verilog_parser-0.0.1.dist-info/LICENSE
verilog_parser-0.0.1.dist-info/METADATA
verilog_parser-0.0.1.dist-info/WHEEL
verilog_parser-0.0.1.dist-info/top_level.txt
verilog_parser-0.0.1.dist-info/RECORD
