Metadata-Version: 2.1
Name: verilog-parser
Version: 0.0.1
Summary: Parser for structural verilog.
Home-page: https://codeberg.org/tok/py-verilog-parser
Author: T. (Benz|Kramer)
Author-email: dont@spam.me
License: AGPL
Keywords: verilog parser
Platform: UNKNOWN
Classifier: License :: OSI Approved :: GNU Affero General Public License v3
Classifier: Development Status :: 3 - Alpha
Classifier: Topic :: Scientific/Engineering
Classifier: Topic :: Scientific/Engineering :: Electronic Design Automation (EDA)
Classifier: Programming Language :: Python :: 3
Requires-Dist: lark-parser
